slimoneat/__init__.py
slimoneat/_version.py
slimoneat/pretrained.py
slimoneat/NEATModels/MidogConfig.py
slimoneat/NEATModels/Staticconfig.py
slimoneat/NEATModels/TrainConfig.py
slimoneat/NEATModels/__init__.py
slimoneat/NEATModels/config.py
slimoneat/NEATModels/gen_anchors.py
slimoneat/NEATModels/loss.py
slimoneat/NEATModels/neat_faststandard.py
slimoneat/NEATModels/neat_focus.py
slimoneat/NEATModels/neat_focus_microscope.py
slimoneat/NEATModels/neat_goldstandard.py
slimoneat/NEATModels/neat_microscope.py
slimoneat/NEATModels/neat_standard.py
slimoneat/NEATModels/neat_static_standard.py
slimoneat/NEATModels/nets.py
slimoneat/NEATUtils/MovieCreator.py
slimoneat/NEATUtils/NMS.py
slimoneat/NEATUtils/SlimViz.py
slimoneat/NEATUtils/__init__.py
slimoneat/NEATUtils/helpers.py
slimoneat/NEATUtils/plotters.py
slimoneat-1.1.2.dist-info/METADATA
slimoneat-1.1.2.dist-info/WHEEL
slimoneat-1.1.2.dist-info/top_level.txt
slimoneat-1.1.2.dist-info/RECORD
