Metadata-Version: 2.1
Name: slimoneat
Version: 1.1.2
Summary: Static and Dynamic classification tool.
Home-page: https://github.com/Kapoorlabs-CAPED/oneat-slim/
Author: Varun Kapoor
Author-email: randomaccessiblekapoor@gmail.com
Classifier: Development Status :: 3 - Alpha
Classifier: Natural Language :: English
Classifier: License :: OSI Approved :: MIT License
Classifier: Operating System :: OS Independent
Classifier: Programming Language :: Python
Classifier: Programming Language :: Python :: 3.9
Requires-Dist: pandas
Requires-Dist: vollseg
Requires-Dist: scipy
Requires-Dist: tifffile
Requires-Dist: matplotlib
Requires-Dist: imagecodecs
Requires-Dist: opencv-python
Requires-Dist: diplib
Requires-Dist: sklearn
Requires-Dist: dask
Requires-Dist: natsort
